globalmart_api/__init__.py
globalmart_api/oops.py
globalmart_api-0.2.dist-info/License.txt
globalmart_api-0.2.dist-info/METADATA
globalmart_api-0.2.dist-info/WHEEL
globalmart_api-0.2.dist-info/top_level.txt
globalmart_api-0.2.dist-info/RECORD
